cvparser/__init__.py
cvparser/cv.py
cvparser/cv_parser.py
cvparser/Enum/__init__.py
cvparser/Enum/filetype.py
cvparser/Enum/language.py
cvparser/extracter/__init__.py
cvparser/extracter/en_extractor.py
cvparser/extracter/extractor.py
cvparser/factories/__init__.py
cvparser/factories/extractor_factory.py
cvparser/factories/parser_factory.py
cvparser/parser/__init__.py
cvparser/parser/doc.py
cvparser/parser/parser.py
cvparser/parser/pdf_parser.py
cvparser/utility/__init__.py
cvparser/utility/ult.py
py_cv_parser-1.1.2.dist-info/licenses/LICENSE
py_cv_parser-1.1.2.dist-info/METADATA
py_cv_parser-1.1.2.dist-info/WHEEL
py_cv_parser-1.1.2.dist-info/top_level.txt
py_cv_parser-1.1.2.dist-info/RECORD
