Metadata-Version: 2.4
Name: py-cv-parser
Version: 1.1.2
Summary: a resume analyze tool
Author-email: hunny <jetchill521@gmail.com>
Project-URL: Homepage, https://github.com/Hunnyisme/cvparser
Classifier: Programming Language :: Python :: 3
Classifier: License :: OSI Approved :: Apache Software License
Classifier: Operating System :: OS Independent
Requires-Python: >=3.8
License-File: LICENSE
Requires-Dist: langdetect~=1.0.9
Requires-Dist: pdfminer.six>=20250506
Requires-Dist: phonenumbers~=9.0.6
Requires-Dist: spacy~=3.8.7
Requires-Dist: country-converter
Dynamic: license-file
